astunparse/__init__.py
astunparse/__main__.py
astunparse/printer.py
astunparse/unparser.py
py_backwards_astunparse-1.5.0.post1.dist-info/DESCRIPTION.rst
py_backwards_astunparse-1.5.0.post1.dist-info/METADATA
py_backwards_astunparse-1.5.0.post1.dist-info/RECORD
py_backwards_astunparse-1.5.0.post1.dist-info/WHEEL
py_backwards_astunparse-1.5.0.post1.dist-info/metadata.json
py_backwards_astunparse-1.5.0.post1.dist-info/top_level.txt
