Metadata-Version: 2.0
Name: py-backwards-astunparse
Version: 1.5.0.post1
Summary: An AST unparser for Python
Home-page: https://github.com/simonpercivall/astunparse
Author: Simon Percivall
Author-email: percivall@gmail.com
License: BSD
Keywords: astunparse
Platform: UNKNOWN
Classifier: Development Status :: 5 - Production/Stable
Classifier: Intended Audience :: Developers
Classifier: License :: OSI Approved :: BSD License
Classifier: Natural Language :: English
Classifier: Programming Language :: Python :: 2
Classifier: Programming Language :: Python :: 2.7
Classifier: Programming Language :: Python :: 3
Classifier: Programming Language :: Python :: 3.3
Classifier: Programming Language :: Python :: 3.4
Classifier: Programming Language :: Python :: 3.5
Classifier: Programming Language :: Python :: 3.6
Classifier: Topic :: Software Development :: Code Generators
Requires-Dist: six (<2.0,>=1.6.1)
Requires-Dist: typed-ast
Requires-Dist: wheel (>=0.23.0,<1.0)
